[
  {
    "Tool": "Move Prover",
    "Category": "Formal Verification",
    "Chain": "Aptos (Move)",
    "Vendor": "Move",
    "License": "Apache-2.0",
    "RepoURL": "https://github.com/move-language/move",
    "MonitorMethod": "GitHub releases",
    "InstallMethod": "cargo | docker",
    "BinaryPath": "",
    "Version": "",
    "FirstSeen": "",
    "AdoptedOn": "",
    "LastUsed": "",
    "LastUpdateCheck": "2025-09-26T05:57:05+00:00",
    "Status": "Quarantined",
    "StatusOn": "2025-09-26T05:57:05+00:00",
    "ReasonCode": "ARCHIVED",
    "Reason": "Upstream repo archived",
    "ReplacedBy": "Security",
    "Owner": "",
    "Notes": null
  },
  {
    "Tool": "Ganache",
    "Category": "Local Node",
    "Chain": "EVM, Base",
    "Vendor": "Truffle Suite",
    "License": "MIT",
    "RepoURL": "https://github.com/trufflesuite/ganache",
    "MonitorMethod": "GitHub releases",
    "InstallMethod": "npm | binary",
    "BinaryPath": "/usr/local/bin/ganache",
    "Version": "v7.9.0",
    "FirstSeen": "",
    "AdoptedOn": "2025-09-24",
    "LastUsed": "",
    "LastUpdateCheck": "2025-09-26T05:57:08+00:00",
    "Status": "Quarantined",
    "StatusOn": "2025-09-26T05:57:08+00:00",
    "ReasonCode": "ARCHIVED",
    "Reason": "Upstream repo archived",
    "ReplacedBy": "",
    "Owner": "Dev",
    "Notes": ""
  },
  {
    "Tool": "Oyente",
    "Category": "Analyzer",
    "Chain": "EVM, Base",
    "Vendor": "Melonport",
    "License": "MIT",
    "RepoURL": "https://github.com/melonproject/oyente",
    "MonitorMethod": "GitHub",
    "InstallMethod": "pip",
    "BinaryPath": "",
    "Version": "0.2.7",
    "FirstSeen": "",
    "AdoptedOn": "",
    "LastUsed": "",
    "LastUpdateCheck": "2025-09-26T05:57:10+00:00",
    "Status": "Quarantined",
    "StatusOn": "2025-09-26T05:57:10+00:00",
    "ReasonCode": "ARCHIVED",
    "Reason": "Upstream repo archived",
    "ReplacedBy": "Security",
    "Owner": "",
    "Notes": null
  }
]